helga_markovify/__init__.py
helga_markovify/markov.py
helga_markovify/plugin.py
helga_markovify/twitter.py
helga_markovify-1.1.1.dist-info/DESCRIPTION.rst
helga_markovify-1.1.1.dist-info/METADATA
helga_markovify-1.1.1.dist-info/RECORD
helga_markovify-1.1.1.dist-info/WHEEL
helga_markovify-1.1.1.dist-info/entry_points.txt
helga_markovify-1.1.1.dist-info/metadata.json
helga_markovify-1.1.1.dist-info/top_level.txt
helga_markovify-1.1.1.dist-info/zip-safe
tests/__init__.py
tests/test_markov.py
tests/test_twitter.py
