Metadata-Version: 2.0
Name: helga-markovify
Version: 1.1.1
Summary: Ingest corpuses of text and output a sentence generated from markov chains
Home-page: https://github.com/narfman0/helga-markovify
Author: Jon Robison
Author-email: narfman0@gmail.com
License: LICENSE
Keywords: irc bot markov
Platform: UNKNOWN
Classifier: Development Status :: 4 - Beta
Classifier: Topic :: Communications :: Chat :: Internet Relay Chat
Classifier: License :: OSI Approved :: GNU General Public License v3 (GPLv3)
Classifier: Operating System :: OS Independent
Classifier: Programming Language :: Python
Classifier: Topic :: Software Development :: Libraries :: Python Modules
Classifier: Topic :: Communications :: Chat :: Internet Relay Chat
Requires-Dist: beautifulsoup4
Requires-Dist: helga
Requires-Dist: helga-log-reader
Requires-Dist: markovify
Requires-Dist: tweepy
